cmkinitramfs/__init__.py
cmkinitramfs/bin.py
cmkinitramfs/data.py
cmkinitramfs/entry.py
cmkinitramfs/init.py
cmkinitramfs/initramfs.py
cmkinitramfs/item.py
cmkinitramfs/utils.py
cmkinitramfs-0.2.4.dist-info/LICENSE.txt
cmkinitramfs-0.2.4.dist-info/METADATA
cmkinitramfs-0.2.4.dist-info/WHEEL
cmkinitramfs-0.2.4.dist-info/entry_points.txt
cmkinitramfs-0.2.4.dist-info/top_level.txt
cmkinitramfs-0.2.4.dist-info/RECORD
