Metadata-Version: 2.1
Name: cmkinitramfs
Version: 0.2.4
Summary: A customizable simple initramfs generator
Home-page: https://github.com/teapot9/cmkinitramfs
Author: Louis Leseur
Author-email: louis.leseur@gmail.com
License: MIT
Keywords: initramfs,initramfs-generator
Platform: Linux
Classifier: Development Status :: 3 - Alpha
Classifier: Environment :: Console
Classifier: Intended Audience :: System Administrators
Classifier: License :: OSI Approved :: MIT License
Classifier: Operating System :: POSIX :: Linux
Classifier: Programming Language :: Python
Classifier: Programming Language :: Python :: 3
Classifier: Programming Language :: Python :: 3.8
Classifier: Programming Language :: Python :: 3.9
Classifier: Programming Language :: Python :: 3.10
Classifier: Programming Language :: Python :: 3.11
Classifier: Programming Language :: Python :: 3.12
Classifier: Programming Language :: Python :: 3.13
Classifier: Programming Language :: Python :: Implementation :: CPython
Classifier: Programming Language :: Python :: Implementation :: PyPy
Classifier: Topic :: System :: Boot
Classifier: Topic :: System :: Boot :: Init
Classifier: Topic :: Utilities
Classifier: Typing :: Typed
Requires-Python: >=3.7, <4
License-File: LICENSE.txt
Requires-Dist: pyelftools
Provides-Extra: doc
Requires-Dist: sphinx ; extra == 'doc'
Requires-Dist: sphinx-rtd-theme ; extra == 'doc'
Provides-Extra: qa
Requires-Dist: flake8 ; extra == 'qa'
Requires-Dist: mypy ; extra == 'qa'
Requires-Dist: tox ; extra == 'qa'
